README.md
setup.py
xcolor/__init__.py
xcolor/colors.py
xcolor/style.py
xcolor/test.py
xcolor/xcolor.py
xcolor.egg-info/PKG-INFO
xcolor.egg-info/SOURCES.txt
xcolor.egg-info/dependency_links.txt
xcolor.egg-info/top_level.txt