Metadata-Version: 2.1
Name: xcolor
Version: 2.1.0
Summary: 终端彩色打印
Home-page: https://github.com/artsoftio/xcolor
Author: Max
Author-email: max@artsoft.io
License: MIT
Keywords: color print ColorPrint python3
Platform: UNKNOWN
Classifier: Programming Language :: Python :: 3
Classifier: Programming Language :: Python :: 3.3
Classifier: Programming Language :: Python :: 3.4
Classifier: Programming Language :: Python :: 3.5
Classifier: Programming Language :: Python :: 3.6
Classifier: Programming Language :: Python :: 3.7
Classifier: Operating System :: POSIX
